{
  "ok": true,
  "news": [
    {
      "title": "Treasury Market Liquidity Since April 2025",
      "url": "https://libertystreeteconomics.newyorkfed.org/2026/04/treasury-market-liquidity-since-april-2025/",
      "desc": "NY Fed Liberty Street Economics reviews how U.S. Treasury market liquidity has evolved over the past year amid economic and political developments, with the Fed balance sheet at $4,407B and TGA at $748B as of April 8, 2026.",
      "date": "2026-04-08"
    },
    {
      "title": "美国隔夜逆回购（ONRRP）接近清零，流动性危机显现",
      "url": "https://xueqiu.com/9216592857/380509790",
      "desc": "分析指出美联储QT持续回收流动性、TGA账户飙升至超9000亿美元吸走大量资金，叠加货币基金从ONRRP撤出转向短债，美元净流动性持续收紧，ONRRP余额接近清零。",
      "date": "2026-03-20"
    },
    {
      "title": "美以伊冲突如何重塑美元流动性格局——从预期路径到现实偏离",
      "url": "http://finance.sina.com.cn/wm/2026-03-27/doc-inhskmqi8556320.shtml",
      "desc": "2026年初市场预计随美联储扩表美元流动性将由紧转松，但2月底"美以伊"冲突使预期失效，驱动逻辑切换至"地缘政治风险定价"模式，一季度美国在岸市场短端流动性承压。",
      "date": "2026-03-27"
    }
  ],
  "fetchedAt": "2026-04-14"
}
